btweak/__init__.py
btweak/data/docker.yaml
btweak/data/tools.yaml
btweak/helpers/cmdhandler.py
btweak/helpers/dockerhandler.py
btweak/helpers/fileparser.py
btweak/helpers/fixthings.py
btweak/helpers/toolhandler.py
btweak/main.py
btweak-0.2.31.dist-info/METADATA
btweak-0.2.31.dist-info/WHEEL
btweak-0.2.31.dist-info/entry_points.txt
btweak-0.2.31.dist-info/RECORD
