Metadata-Version: 2.4
Name: btweak
Version: 0.2.31
Summary: Berserk Arch Tweak Tool
License-Expression: GPL-3.0-or-later
Author: Gaurav Raj
Author-email: gauravraj0408@gmail.com
Requires-Python: >=3.8
Classifier: Programming Language :: Python :: 3
Classifier: Programming Language :: Python :: 3.8
Classifier: Programming Language :: Python :: 3.9
Classifier: Programming Language :: Python :: 3.10
Classifier: Programming Language :: Python :: 3.11
Classifier: Programming Language :: Python :: 3.12
Classifier: Programming Language :: Python :: 3.13
Classifier: Programming Language :: Python :: 3.14
Requires-Dist: pyyaml (>=6.0.3,<7.0.0)
Requires-Dist: rich (>=14.2.0,<15.0.0)
